[
  {
    "id": 1,
    "type": "choice",
    "category": "第一章 进入近代后中华民族的磨难与抗争",
    "difficulty": "medium",
    "question": "中国封建社会的基本生产结构（）",
    "options": [
      "以个体家庭为单位并与家庭手工业牢固结合的小农经济",
      "自给自足的自然经济",
      "封建地主土地所有制",
      "土地私有制度"
    ],
    "answer": 0,
    "explanation": "正确答案是 A。以个体家庭为单位并与家庭手工业牢固结合的小农经济"
  },
  {
    "id": 2,
    "type": "choice",
    "category": "第一章 进入近代后中华民族的磨难与抗争",
    "difficulty": "medium",
    "question": "（）标志着世界历史开始进入资本主义时代",
    "options": [
      "英国光荣革命",
      "第一次工业革命",
      "地理大发现",
      "英国资产阶级革命"
    ],
    "answer": 3,
    "explanation": "正确答案是 D。英国资产阶级革命"
  },
  {
    "id": 3,
    "type": "choice",
    "category": "第一章 进入近代后中华民族的磨难与抗争",
    "difficulty": "medium",
    "question": "19世纪末资本主义进入帝国主义阶段后，（）成为殖民主义剥削的重要形式，并出现瓜分世界的狂潮",
    "options": [
      "商品输出",
      "资本输出",
      "贩卖奴隶",
      "掠夺土地"
    ],
    "answer": 1,
    "explanation": "正确答案是 B。资本输出"
  },
  {
    "id": 4,
    "type": "choice",
    "category": "第一章 进入近代后中华民族的磨难与抗争",
    "difficulty": "medium",
    "question": "鸦片战争以清政府的失败而告终。1842年8月29日，清政府与英国签订了中国近代史上的第一个不平等条约是（）",
    "options": [
      "中英《南京条约》",
      "中英《虎门条约》",
      "中美《望厦条约》",
      "中法《黄埔条约》"
    ],
    "answer": 0,
    "explanation": "正确答案是 A。中英《南京条约》"
  },
  {
    "id": 5,
    "type": "choice",
    "category": "第一章 进入近代后中华民族的磨难与抗争",
    "difficulty": "medium",
    "question": "鸦片战争后，中国经济逐渐被卷入世界资本主义市场，其对中国的影响不包括（）",
    "options": [
      "自给自足的自然经济逐步解体",
      "西方的先进生产技术逐步传入中国",
      "英国对华输出商品激增",
      "封建地主土地所有制瓦解"
    ],
    "answer": 3,
    "explanation": "正确答案是 D。封建地主土地所有制瓦解"
  },
  {
    "id": 6,
    "type": "choice",
    "category": "第一章 进入近代后中华民族的磨难与抗争",
    "difficulty": "medium",
    "question": "中国工人阶级最早出现于（）",
    "options": [
      "19世纪30至40年代",
      "19世纪40至50年代",
      "19世纪50至60年代",
      "19世纪60至70年代"
    ],
    "answer": 1,
    "explanation": "正确答案是 B。19世纪40至50年代"
  },
  {
    "id": 7,
    "type": "choice",
    "category": "第一章 进入近代后中华民族的磨难与抗争",
    "difficulty": "medium",
    "question": "中国资产阶级也是近代中国新产生的阶级。它的来源不包括（）",
    "options": [
      "买办",
      "商人",
      "地主",
      "城市工商业者"
    ],
    "answer": 3,
    "explanation": "正确答案是 D。城市工商业者"
  },
  {
    "id": 8,
    "type": "choice",
    "category": "第一章 进入近代后中华民族的磨难与抗争",
    "difficulty": "medium",
    "question": "1860年《北京条约》又规定增加开放（）为通商口岸",
    "options": [
      "天津",
      "烟台",
      "营口",
      "台南"
    ],
    "answer": 0,
    "explanation": "正确答案是 A。天津"
  },
  {
    "id": 9,
    "type": "choice",
    "category": "第一章 进入近代后中华民族的磨难与抗争",
    "difficulty": "medium",
    "question": "资本-帝国主义对中国的军事侵略包括：发动侵略战争，屠杀中国人民；（）；勒索赔款，抢掠财富",
    "options": [
      "侵占中国领土，划分势力范围",
      "享有最惠国待遇",
      "镇压中国人民的反抗",
      "扶植、收买代理人"
    ],
    "answer": 0,
    "explanation": "正确答案是 A。侵占中国领土，划分势力范围"
  },
  {
    "id": 10,
    "type": "choice",
    "category": "第一章 进入近代后中华民族的磨难与抗争",
    "difficulty": "medium",
    "question": "1843年（）规定，在通商口岸，中国人如与英侨\"遇有交涉诉讼\"，英国领事有\"查察\"\"听诉\"之权",
    "options": [
      "《望厦条约》",
      "《五口通商章程》",
      "《烟台条约》",
      "《虎门条约》"
    ],
    "answer": 1,
    "explanation": "正确答案是 B。《五口通商章程》"
  },
  {
    "id": 11,
    "type": "choice",
    "category": "第一章 进入近代后中华民族的磨难与抗争",
    "difficulty": "medium",
    "question": "广学会发行的刊物（），在介绍西方史地、政治、文化的同时，也宣扬殖民主义奴化思想",
    "options": [
      "《万国公报》",
      "《中外纪闻》",
      "《印度隶英十二益说》",
      "《泰西新史揽要》"
    ],
    "answer": 0,
    "explanation": "正确答案是 A。《万国公报》"
  },
  {
    "id": 12,
    "type": "choice",
    "category": "第一章 进入近代后中华民族的磨难与抗争",
    "difficulty": "medium",
    "question": "（），是外国侵略者控制中国政治的重要手段之一",
    "options": [
      "奴化教育",
      "把持中国海关",
      "门户开放政策",
      "签订不平等条约"
    ],
    "answer": 1,
    "explanation": "正确答案是 B。把持中国海关"
  },
  {
    "id": 13,
    "type": "choice",
    "category": "第一章 进入近代后中华民族的磨难与抗争",
    "difficulty": "medium",
    "question": "洋货只需在海关交纳2.5%的（），就可以在中国内地通行无阻",
    "options": [
      "关税",
      "海关税",
      "厘金",
      "子口税"
    ],
    "answer": 3,
    "explanation": "正确答案是 D。子口税"
  },
  {
    "id": 14,
    "type": "choice",
    "category": "第一章 进入近代后中华民族的磨难与抗争",
    "difficulty": "medium",
    "question": "（），是中国近代史上中国人民第一次大规模的反侵略武装斗争",
    "options": [
      "虎门销烟",
      "三元里人民抗英斗争",
      "太平天国运动",
      "义和团运动"
    ],
    "answer": 1,
    "explanation": "正确答案是 B。三元里人民抗英斗争"
  },
  {
    "id": 15,
    "type": "choice",
    "category": "第一章 进入近代后中华民族的磨难与抗争",
    "difficulty": "medium",
    "question": "资本主义列强还通过（），传播其价值理念",
    "options": [
      "兴办教育",
      "发展失业",
      "国民教育",
      "创建学校"
    ],
    "answer": 0,
    "explanation": "正确答案是 A。兴办教育"
  },
  {
    "id": 16,
    "type": "choice",
    "category": "第一章 进入近代后中华民族的磨难与抗争",
    "difficulty": "medium",
    "question": "从1840年至1919年的80年间，中国人民对外来侵略进行了英勇顽强的反抗，这些斗争具有重大的历史作用。因为正是由于（），才使得经济技术落后的状况长期得不到改变",
    "options": [
      "社会制度的腐败",
      "清王朝的腐朽",
      "不了解世界大势",
      "不懂得御敌之策"
    ],
    "answer": 0,
    "explanation": "正确答案是 A。社会制度的腐败"
  },
  {
    "id": 17,
    "type": "choice",
    "category": "第一章 进入近代后中华民族的磨难与抗争",
    "difficulty": "medium",
    "question": "帝国主义侵略中国的最终目的，是要（）",
    "options": [
      "帮助中国发展资本主义",
      "传播西方先进文化",
      "为本国资本主义发展寻求市场和原料产地",
      "瓜分中国，灭亡中国"
    ],
    "answer": 3,
    "explanation": "正确答案是 D。瓜分中国，灭亡中国"
  },
  {
    "id": 18,
    "type": "choice",
    "category": "第一章 进入近代后中华民族的磨难与抗争",
    "difficulty": "medium",
    "question": "郑观应在所著（）中提出大力发展民族工商业，同西方国家进行\"商战\"，设立议院，实行\"君民共主\"制度等主张",
    "options": [
      "《劝学篇》",
      "《劝世良言》",
      "《盛世危言》",
      "《救亡决论》"
    ],
    "answer": 2,
    "explanation": "正确答案是 C。《盛世危言》"
  },
  {
    "id": 19,
    "type": "choice",
    "category": "第一章 进入近代后中华民族的磨难与抗争",
    "difficulty": "medium",
    "question": "康有为1898年4月在（）的演说中把民族意识表达得淋漓尽致",
    "options": [
      "保国会",
      "强学会",
      "日知会",
      "广学会"
    ],
    "answer": 0,
    "explanation": "正确答案是 A。保国会"
  },
  {
    "id": 20,
    "type": "choice",
    "category": "第一章 进入近代后中华民族的磨难与抗争",
    "difficulty": "medium",
    "question": "孙中山1894年11月在创立革命团体兴中会时喊出了（）这个时代的最强音",
    "options": [
      "振兴中国",
      "伟大复兴",
      "振兴中华",
      "民族复兴"
    ],
    "answer": 2,
    "explanation": "正确答案是 C。振兴中华"
  },
  {
    "id": 21,
    "type": "multiChoice",
    "category": "第一章 进入近代后中华民族的磨难与抗争",
    "difficulty": "medium",
    "question": "中国封建社会的社会结构特点是族权和政权相结合的封建宗法等级制度。其核心是宗族家长制，突出（）",
    "options": [
      "父权",
      "夫权",
      "君权",
      "族长权"
    ],
    "answer": [
      0,
      1,
      2
    ],
    "explanation": "正确答案是 A, B, C。"
  },
  {
    "id": 22,
    "type": "multiChoice",
    "category": "第一章 进入近代后中华民族的磨难与抗争",
    "difficulty": "medium",
    "question": "资本-帝国主义列强在对中国进行文化渗透的目的包括（）",
    "options": [
      "宣扬殖民主义奴化思想",
      "麻醉中国人民的精神",
      "进行侵略活动宣传宗教和西学",
      "摧毁中国人的民族自尊心和自信心"
    ],
    "answer": [
      0,
      1,
      3
    ],
    "explanation": "正确答案是 A, B, D。"
  },
  {
    "id": 23,
    "type": "multiChoice",
    "category": "第一章 进入近代后中华民族的磨难与抗争",
    "difficulty": "medium",
    "question": "中国政府举借外债，主要是以（）和（）为担保",
    "options": [
      "关税",
      "厂矿",
      "盐税",
      "航运"
    ],
    "answer": [
      0,
      2
    ],
    "explanation": "正确答案是 A, C。"
  },
  {
    "id": 24,
    "type": "multiChoice",
    "category": "第一章 进入近代后中华民族的磨难与抗争",
    "difficulty": "medium",
    "question": "资本-帝国主义列强对中国进行经济侵略的方式主要有（）",
    "options": [
      "控制中国的通商口岸",
      "剥夺中国的关税自主权",
      "实行商品倾销和资本输出",
      "操纵中国的经济命脉"
    ],
    "answer": [
      0,
      1,
      2,
      3
    ],
    "explanation": "正确答案是 A, B, C, D。"
  },
  {
    "id": 25,
    "type": "multiChoice",
    "category": "第一章 进入近代后中华民族的磨难与抗争",
    "difficulty": "medium",
    "question": "在中法战争后期，1885年3月，爱国将领冯子材指挥清军取得（）和（）",
    "options": [
      "镇南关大捷",
      "谅山大捷",
      "宁远大捷",
      "徐东大捷"
    ],
    "answer": [
      0,
      1
    ],
    "explanation": "正确答案是 A, B。"
  },
  {
    "id": 26,
    "type": "multiChoice",
    "category": "第一章 进入近代后中华民族的磨难与抗争",
    "difficulty": "medium",
    "question": "19世纪50～80年代，俄国共侵占我国领土150多万平方公里，这主要是通过（）完成的",
    "options": [
      "《瑷辉条约》",
      "《北京条约》",
      "《勘分西北界约记》",
      "《改订伊犁条约》"
    ],
    "answer": [
      0,
      1,
      2,
      3
    ],
    "explanation": "正确答案是 A, B, C, D。"
  },
  {
    "id": 27,
    "type": "multiChoice",
    "category": "第一章 进入近代后中华民族的磨难与抗争",
    "difficulty": "medium",
    "question": "三国干涉还辽的三国包括（）",
    "options": [
      "英国",
      "俄国",
      "法国",
      "德国"
    ],
    "answer": [
      1,
      2,
      3
    ],
    "explanation": "正确答案是 B, C, D。"
  },
  {
    "id": 28,
    "type": "multiChoice",
    "category": "第一章 进入近代后中华民族的磨难与抗争",
    "difficulty": "medium",
    "question": "19世纪70至80年代，列强从侵占中国周边邻国发展到蚕食中国边疆地区（）",
    "options": [
      "英国从印度侵入西藏",
      "又从缅甸入侵云南",
      "法国则从越南侵犯广西",
      "葡萄牙占领澳门"
    ],
    "answer": [
      0,
      1,
      2
    ],
    "explanation": "正确答案是 A, B, C。"
  },
  {
    "id": 29,
    "type": "multiChoice",
    "category": "第一章 进入近代后中华民族的磨难与抗争",
    "difficulty": "medium",
    "question": "魏源在1843年1月编成（），其内容包括世界各国的历史、地理，还有总结鸦片战争经验教训的（），翻译西人论述的（）及西洋科技船炮图说等",
    "options": [
      "《海国图志》",
      "《筹海篇》",
      "《夷情备采》",
      "《康蝤纪行》"
    ],
    "answer": [
      0,
      1,
      2
    ],
    "explanation": "正确答案是 A, B, C。"
  },
  {
    "id": 30,
    "type": "multiChoice",
    "category": "第一章 进入近代后中华民族的磨难与抗争",
    "difficulty": "medium",
    "question": "近代中国人民的反侵略战争（）",
    "options": [
      "沉重地打击了资本—帝国主义列强的侵华野心",
      "使我们的国家和民族历尽劫难、屡遭侵略而不亡",
      "它表现出来的爱国主义精神，铸成了中华民族的民族魂",
      "反侵略战争的失败，从反面教育了中国人民，极大地促进了中国人的思考、探索和奋起"
    ],
    "answer": [
      1,
      2,
      3
    ],
    "explanation": "正确答案是 B, C, D。"
  }
]